odoo/addons/sale_order_secondary_unit/README.rst
odoo/addons/sale_order_secondary_unit/__init__.py
odoo/addons/sale_order_secondary_unit/__manifest__.py
odoo/addons/sale_order_secondary_unit/i18n/es.po
odoo/addons/sale_order_secondary_unit/i18n/sale_order_secondary_unit.pot
odoo/addons/sale_order_secondary_unit/migrations/11.0.1.0.2/post-migration.py
odoo/addons/sale_order_secondary_unit/models/__init__.py
odoo/addons/sale_order_secondary_unit/models/product_template.py
odoo/addons/sale_order_secondary_unit/models/sale_order.py
odoo/addons/sale_order_secondary_unit/readme/CONTRIBUTORS.rst
odoo/addons/sale_order_secondary_unit/readme/DESCRIPTION.rst
odoo/addons/sale_order_secondary_unit/readme/USAGE.rst
odoo/addons/sale_order_secondary_unit/static/description/icon.png
odoo/addons/sale_order_secondary_unit/static/description/index.html
odoo/addons/sale_order_secondary_unit/tests/__init__.py
odoo/addons/sale_order_secondary_unit/tests/test_sale_order_secondary_unit.py
odoo/addons/sale_order_secondary_unit/views/product_views.xml
odoo/addons/sale_order_secondary_unit/views/sale_order_views.xml
odoo11_addon_sale_order_secondary_unit-11.0.1.0.2.dist-info/METADATA
odoo11_addon_sale_order_secondary_unit-11.0.1.0.2.dist-info/RECORD
odoo11_addon_sale_order_secondary_unit-11.0.1.0.2.dist-info/WHEEL
odoo11_addon_sale_order_secondary_unit-11.0.1.0.2.dist-info/top_level.txt
