Metadata-Version: 2.1
Name: odoo11-addon-sale-order-secondary-unit
Version: 11.0.1.0.2
Summary: Sale product in a secondary unit
Home-page: https://github.com/OCA/sale-workflow
Author: Tecnativa, Odoo Community Association (OCA)
Author-email: support@odoo-community.org
License: AGPL-3
Platform: UNKNOWN
Classifier: Programming Language :: Python
Classifier: Framework :: Odoo
Classifier: License :: OSI Approved :: GNU Affero General Public License v3
Classifier: Development Status :: 4 - Beta
Requires-Python: >=2.7, !=3.0.*, !=3.1.*, !=3.2.*, !=3.3.*, !=3.4.*
Requires-Dist: odoo11-addon-product-secondary-unit
Requires-Dist: odoo (<11.1dev,>=11.0a)
